site_analysis/__init__.py
site_analysis/atom.py
site_analysis/builders.py
site_analysis/dynamic_voronoi_site.py
site_analysis/dynamic_voronoi_site_collection.py
site_analysis/pbc_utils.py
site_analysis/polyhedral_site.py
site_analysis/polyhedral_site_collection.py
site_analysis/site.py
site_analysis/site_collection.py
site_analysis/spherical_site.py
site_analysis/spherical_site_collection.py
site_analysis/tools.py
site_analysis/trajectory.py
site_analysis/voronoi_site.py
site_analysis/voronoi_site_collection.py
site_analysis/reference_workflow/__init__.py
site_analysis/reference_workflow/coord_finder.py
site_analysis/reference_workflow/index_mapper.py
site_analysis/reference_workflow/reference_based_sites.py
site_analysis/reference_workflow/site_factory.py
site_analysis/reference_workflow/structure_aligner.py
site_analysis-1.2.5.dist-info/licenses/LICENSE
site_analysis-1.2.5.dist-info/METADATA
site_analysis-1.2.5.dist-info/WHEEL
site_analysis-1.2.5.dist-info/top_level.txt
site_analysis-1.2.5.dist-info/RECORD
