Metadata-Version: 2.4
Name: site_analysis
Version: 1.2.5
Summary: Analysis tools for tracking ion migration through crystallographic sites
Author-email: "Benjamin J. Morgan" <b.j.morgan@bath.ac.uk>
License-Expression: MIT
Project-URL: Homepage, https://github.com/bjmorgan/site_analysis
Project-URL: Bug Tracker, https://github.com/bjmorgan/site_analysis/issues
Classifier: Programming Language :: Python :: 3
Classifier: Operating System :: OS Independent
Requires-Python: >=3.10
License-File: LICENSE
Requires-Dist: numpy
Requires-Dist: scipy
Requires-Dist: pymatgen
Requires-Dist: tqdm
Requires-Dist: monty
Provides-Extra: dev
Requires-Dist: pytest; extra == "dev"
Requires-Dist: coverage; extra == "dev"
Requires-Dist: pytest-cov; extra == "dev"
Requires-Dist: mypy; extra == "dev"
Requires-Dist: types-PyYAML; extra == "dev"
Requires-Dist: sphinx; extra == "dev"
Requires-Dist: nbsphinx; extra == "dev"
Requires-Dist: sphinx-rtd-theme; extra == "dev"
Requires-Dist: myst-parser; extra == "dev"
Requires-Dist: matplotlib; extra == "dev"
Dynamic: license-file
